pydistsim/__init__.py
pydistsim/_exceptions.py
pydistsim/benchmark.py
pydistsim/logging.py
pydistsim/message.py
pydistsim/metrics.py
pydistsim/observers.py
pydistsim/simulation.py
pydistsim/algorithm/__init__.py
pydistsim/algorithm/base_algorithm.py
pydistsim/algorithm/network_algorithm.py
pydistsim/algorithm/node_algorithm.py
pydistsim/algorithm/node_wrapper.py
pydistsim/conf/ipython/__init__.py
pydistsim/conf/ipython/ipython_config.py
pydistsim/conf/ipython/ipython_notebook_config.py
pydistsim/demo_algorithms/__init__.py
pydistsim/demo_algorithms/broadcast.py
pydistsim/demo_algorithms/readsensors.py
pydistsim/demo_algorithms/niculescu2003/__init__.py
pydistsim/demo_algorithms/niculescu2003/dvhop.py
pydistsim/demo_algorithms/niculescu2003/floodingupdate.py
pydistsim/demo_algorithms/niculescu2003/trilaterate.py
pydistsim/demo_algorithms/santoro2007/__init__.py
pydistsim/demo_algorithms/santoro2007/traversal.py
pydistsim/demo_algorithms/santoro2007/yoyo.py
pydistsim/demo_algorithms/santoro2007/mega_merger/__init__.py
pydistsim/demo_algorithms/santoro2007/mega_merger/algorithm.py
pydistsim/demo_algorithms/santoro2007/mega_merger/labels.py
pydistsim/demo_algorithms/tests/__init__.py
pydistsim/demo_algorithms/tests/test_broadcast.py
pydistsim/demo_algorithms/tests/test_mega_merger.py
pydistsim/demo_algorithms/tests/test_niculescu2003.py
pydistsim/demo_algorithms/tests/test_santoro2007.py
pydistsim/gui/__init__.py
pydistsim/gui/__main__.py
pydistsim/gui/dictionarytreemodel.py
pydistsim/gui/drawing.py
pydistsim/gui/icons_rc.py
pydistsim/gui/simulation.ui.py
pydistsim/gui/simulationgui.py
pydistsim/gui/simulationui.py
pydistsim/network/__init__.py
pydistsim/network/behavior.py
pydistsim/network/environment.py
pydistsim/network/generator.py
pydistsim/network/network.py
pydistsim/network/node.py
pydistsim/network/rangenetwork.py
pydistsim/network/sensor.py
pydistsim/restrictions/__init__.py
pydistsim/restrictions/axioms.py
pydistsim/restrictions/base_restriction.py
PyDistSim-2.1.2.dist-info/LICENSE.txt
PyDistSim-2.1.2.dist-info/METADATA
PyDistSim-2.1.2.dist-info/WHEEL
PyDistSim-2.1.2.dist-info/entry_points.txt
PyDistSim-2.1.2.dist-info/top_level.txt
PyDistSim-2.1.2.dist-info/RECORD
