Metadata-Version: 2.1
Name: PyDistSim
Version: 2.1.2
Summary: A high-level Python library for simulation of distributed algorithms.
Author-email: Agustin Recoba <agustin.recoba@outlook.com>, Damir Arbula <damir.arbula@gmail.com>
Project-URL: Homepage, https://github.com/agustin-recoba/pydistsim
Project-URL: Issues, https://github.com/agustin-recoba/pydistsim/issues
Project-URL: Documentation, https://pydistsim.readthedocs.io/
Project-URL: Repository, https://github.com/agustin-recoba/pydistsim.git
Project-URL: CI-CD, https://app.travis-ci.com/github/agustin-recoba/pydistsim/
Project-URL: Test Coverage, https://coveralls.io/github/agustin-recoba/PyDistSim
Keywords: Networks,Distributed algorithms
Classifier: Intended Audience :: Developers
Classifier: Intended Audience :: Science/Research
Classifier: Operating System :: OS Independent
Classifier: Programming Language :: Python :: 3.11
Classifier: Topic :: Software Development :: Libraries :: Python Modules
Classifier: Topic :: System :: Distributed Computing
Classifier: Topic :: System :: Networking
Classifier: Topic :: Scientific/Engineering :: Information Analysis
Requires-Python: >=3.11
License-File: LICENSE.txt
Requires-Dist: ipython==8.26.0
Requires-Dist: ipykernel==6.29.5
Requires-Dist: matplotlib==3.9.2
Requires-Dist: networkx==3.3
Requires-Dist: numpy==2.1.0
Requires-Dist: pandas==2.2.2
Requires-Dist: seaborn==0.13.2
Requires-Dist: scipy==1.14.1
Requires-Dist: loguru==0.7.2
Requires-Dist: pypng==0.20220715.0
Provides-Extra: dev
Requires-Dist: pytest==8.2.0; extra == "dev"
Requires-Dist: pytest-cov==5.0.0; extra == "dev"
Requires-Dist: pytest-sugar==1.0.0; extra == "dev"
Requires-Dist: virtualenv==20.26.3; extra == "dev"
Requires-Dist: coverage==7.6.1; extra == "dev"
Requires-Dist: pre-commit==3.8.0; extra == "dev"
Requires-Dist: pytest-xdist==3.6.1; extra == "dev"
Provides-Extra: gui
Requires-Dist: PySide6==6.7.2; extra == "gui"
